[{"LONGITUDE":135.3,"LATITUDE":12.8,"ISSUEDATE":"/Date(1686052800000)/","WIND":18,"AIRPRESSURE":1000,"MOVESPEED":22},{"LONGITUDE":134.8,"LATITUDE":14.2,"ISSUEDATE":"/Date(1686074400000)/","WIND":20,"AIRPRESSURE":998,"MOVESPEED":15},{"LONGITUDE":134.7,"LATITUDE":14.7,"ISSUEDATE":"/Date(1686085200000)/","WIND":20,"AIRPRESSURE":998,"MOVESPEED":14},{"LONGITUDE":134.2,"LATITUDE":14.9,"ISSUEDATE":"/Date(1686096000000)/","WIND":23,"AIRPRESSURE":990,"MOVESPEED":13},{"LONGITUDE":134.1,"LATITUDE":15,"ISSUEDATE":"/Date(1686117600000)/","WIND":25,"AIRPRESSURE":985,"MOVESPEED":14},{"LONGITUDE":133.4,"LATITUDE":15.4,"ISSUEDATE":"/Date(1686128400000)/","WIND":25,"AIRPRESSURE":985,"MOVESPEED":11},{"LONGITUDE":133.1,"LATITUDE":15.5,"ISSUEDATE":"/Date(1686139200000)/","WIND":25,"AIRPRESSURE":985,"MOVESPEED":11},{"LONGITUDE":132.2,"LATITUDE":15.5,"ISSUEDATE":"/Date(1686160800000)/","WIND":28,"AIRPRESSURE":982,"MOVESPEED":10},{"LONGITUDE":132,"LATITUDE":15.8,"ISSUEDATE":"/Date(1686171600000)/","WIND":28,"AIRPRESSURE":982,"MOVESPEED":10},{"LONGITUDE":131.5,"LATITUDE":16,"ISSUEDATE":"/Date(1686182400000)/","WIND":30,"AIRPRESSURE":980,"MOVESPEED":8},{"LONGITUDE":131.3,"LATITUDE":16.1,"ISSUEDATE":"/Date(1686193200000)/","WIND":30,"AIRPRESSURE":980,"MOVESPEED":9},{"LONGITUDE":131.2,"LATITUDE":16.2,"ISSUEDATE":"/Date(1686204000000)/","WIND":33,"AIRPRESSURE":975,"MOVESPEED":8},{"LONGITUDE":131,"LATITUDE":16.3,"ISSUEDATE":"/Date(1686214800000)/","WIND":35,"AIRPRESSURE":970,"MOVESPEED":8},{"LONGITUDE":130.7,"LATITUDE":16.4,"ISSUEDATE":"/Date(1686225600000)/","WIND":38,"AIRPRESSURE":965,"MOVESPEED":8},{"LONGITUDE":130.6,"LATITUDE":16.6,"ISSUEDATE":"/Date(1686236400000)/","WIND":38,"AIRPRESSURE":965,"MOVESPEED":8},{"LONGITUDE":130.3,"LATITUDE":16.8,"ISSUEDATE":"/Date(1686247200000)/","WIND":38,"AIRPRESSURE":965,"MOVESPEED":9},{"LONGITUDE":130.2,"LATITUDE":17,"ISSUEDATE":"/Date(1686258000000)/","WIND":38,"AIRPRESSURE":965,"MOVESPEED":8},{"LONGITUDE":130.2,"LATITUDE":17.3,"ISSUEDATE":"/Date(1686268800000)/","WIND":38,"AIRPRESSURE":965,"MOVESPEED":6},{"LONGITUDE":130.2,"LATITUDE":17.5,"ISSUEDATE":"/Date(1686279600000)/","WIND":38,"AIRPRESSURE":965,"MOVESPEED":8},{"LONGITUDE":130.1,"LATITUDE":18,"ISSUEDATE":"/Date(1686290400000)/","WIND":38,"AIRPRESSURE":965,"MOVESPEED":6},{"LONGITUDE":130,"LATITUDE":18.1,"ISSUEDATE":"/Date(1686301200000)/","WIND":38,"AIRPRESSURE":965,"MOVESPEED":7},{"LONGITUDE":129.9,"LATITUDE":18.2,"ISSUEDATE":"/Date(1686312000000)/","WIND":38,"AIRPRESSURE":965,"MOVESPEED":10},{"LONGITUDE":129.9,"LATITUDE":18.3,"ISSUEDATE":"/Date(1686322800000)/","WIND":38,"AIRPRESSURE":965,"MOVESPEED":12},{"LONGITUDE":129.9,"LATITUDE":18.5,"ISSUEDATE":"/Date(1686333600000)/","WIND":40,"AIRPRESSURE":960,"MOVESPEED":13},{"LONGITUDE":129.9,"LATITUDE":18.7,"ISSUEDATE":"/Date(1686344400000)/","WIND":40,"AIRPRESSURE":960,"MOVESPEED":14},{"LONGITUDE":129.9,"LATITUDE":18.9,"ISSUEDATE":"/Date(1686355200000)/","WIND":40,"AIRPRESSURE":960,"MOVESPEED":15},{"LONGITUDE":130.1,"LATITUDE":19.4,"ISSUEDATE":"/Date(1686366000000)/","WIND":40,"AIRPRESSURE":960,"MOVESPEED":15},{"LONGITUDE":130.2,"LATITUDE":19.9,"ISSUEDATE":"/Date(1686376800000)/","WIND":40,"AIRPRESSURE":960,"MOVESPEED":16},{"LONGITUDE":130.4,"LATITUDE":20.4,"ISSUEDATE":"/Date(1686387600000)/","WIND":40,"AIRPRESSURE":960,"MOVESPEED":18},{"LONGITUDE":130.7,"LATITUDE":20.9,"ISSUEDATE":"/Date(1686398400000)/","WIND":38,"AIRPRESSURE":965,"MOVESPEED":20},{"LONGITUDE":130.9,"LATITUDE":21.2,"ISSUEDATE":"/Date(1686409200000)/","WIND":38,"AIRPRESSURE":965,"MOVESPEED":22},{"LONGITUDE":131.1,"LATITUDE":21.7,"ISSUEDATE":"/Date(1686420000000)/","WIND":38,"AIRPRESSURE":965,"MOVESPEED":23},{"LONGITUDE":131.3,"LATITUDE":22.2,"ISSUEDATE":"/Date(1686430800000)/","WIND":38,"AIRPRESSURE":965,"MOVESPEED":24},{"LONGITUDE":131.8,"LATITUDE":22.9,"ISSUEDATE":"/Date(1686441600000)/","WIND":35,"AIRPRESSURE":970,"MOVESPEED":30},{"LONGITUDE":132.6,"LATITUDE":24.1,"ISSUEDATE":"/Date(1686463200000)/","WIND":35,"AIRPRESSURE":970,"MOVESPEED":30},{"LONGITUDE":133.1,"LATITUDE":24.7,"ISSUEDATE":"/Date(1686474000000)/","WIND":33,"AIRPRESSURE":975,"MOVESPEED":35},{"LONGITUDE":133.9,"LATITUDE":25.6,"ISSUEDATE":"/Date(1686484800000)/","WIND":30,"AIRPRESSURE":980,"MOVESPEED":36},{"LONGITUDE":135,"LATITUDE":26.4,"ISSUEDATE":"/Date(1686506400000)/","WIND":30,"AIRPRESSURE":980,"MOVESPEED":39},{"LONGITUDE":136,"LATITUDE":27.2,"ISSUEDATE":"/Date(1686517200000)/","WIND":30,"AIRPRESSURE":980,"MOVESPEED":46},{"LONGITUDE":137.2,"LATITUDE":27.9,"ISSUEDATE":"/Date(1686528000000)/","WIND":30,"AIRPRESSURE":980,"MOVESPEED":44},{"LONGITUDE":137.6,"LATITUDE":29.1,"ISSUEDATE":"/Date(1686549600000)/","WIND":28,"AIRPRESSURE":982,"MOVESPEED":43},{"LONGITUDE":138.5,"LATITUDE":30,"ISSUEDATE":"/Date(1686560400000)/","WIND":25,"AIRPRESSURE":985,"MOVESPEED":44},{"LONGITUDE":139.3,"LATITUDE":30.3,"ISSUEDATE":"/Date(1686571200000)/","WIND":23,"AIRPRESSURE":990,"MOVESPEED":43}]